operationunitaire/__init__.py
operationunitaire/__main__.py
operationunitaire/main.py
operationunitaire/core/__init__.py
operationunitaire/core/coefficients.py
operationunitaire/core/data_loader.py
operationunitaire/core/interpolation.py
operationunitaire/core/solver.py
operationunitaire/core/tridiagonal.py
operationunitaire/core/variables.py
operationunitaire/data/C3.csv
operationunitaire/data/IC4.csv
operationunitaire/data/IC5.csv
operationunitaire/data/NC4.csv
operationunitaire/data/NC5.csv
operationunitaire/data/NC6.csv
operationunitaire/data/NC7.csv
operationunitaire/data/NC8.csv
operationunitaire/data/NC9.csv
operationunitaire/utils/__init__.py
operationunitaire/utils/display.py
operationunitaire-0.2.5.dist-info/METADATA
operationunitaire-0.2.5.dist-info/WHEEL
operationunitaire-0.2.5.dist-info/licenses/LICENSE.txt
operationunitaire-0.2.5.dist-info/RECORD
