Metadata-Version: 2.4
Name: operationunitaire
Version: 0.2.5
Summary: A Python package for rigorous distillation simulations.
Project-URL: Homepage, https://github.com/anastassaoui/operationunitaire
Project-URL: Issues, https://github.com/anastassaoui/operationunitaire/issues
Author-email: Tassaoui Anas <anass.tassaoui@gmail.com>
License-File: LICENSE.txt
Classifier: License :: OSI Approved :: GNU Affero General Public License v3
Classifier: Operating System :: OS Independent
Classifier: Programming Language :: Python :: 3
Classifier: Topic :: Scientific/Engineering :: Chemistry
Requires-Python: >=3.7
Requires-Dist: numpy>=1.18
Requires-Dist: pandas>=1.0
Requires-Dist: scipy>=1.5
Requires-Dist: setuptools>=40.0
Requires-Dist: tabulate>=0.8
